MANIFEST.in
README.md
setup.py
mjc_mwe/__init__.py
mjc_mwe/ant.py
mjc_mwe/half_cheetah.py
mjc_mwe/hopper.py
mjc_mwe/humanoid.py
mjc_mwe/humanoid_standup.py
mjc_mwe/inverted_double_pendulum.py
mjc_mwe/inverted_pendulum.py
mjc_mwe/mujoco_env.py
mjc_mwe/pusher.py
mjc_mwe/reacher.py
mjc_mwe/swimmer.py
mjc_mwe/walker2d.py
mjc_mwe.egg-info/PKG-INFO
mjc_mwe.egg-info/SOURCES.txt
mjc_mwe.egg-info/dependency_links.txt
mjc_mwe.egg-info/not-zip-safe
mjc_mwe.egg-info/requires.txt
mjc_mwe.egg-info/top_level.txt
mjc_mwe/assets/ant.xml
mjc_mwe/assets/half_cheetah.xml
mjc_mwe/assets/hopper.xml
mjc_mwe/assets/humanoid.xml
mjc_mwe/assets/humanoidstandup.xml
mjc_mwe/assets/inverted_double_pendulum.xml
mjc_mwe/assets/inverted_pendulum.xml
mjc_mwe/assets/point.xml
mjc_mwe/assets/pusher.xml
mjc_mwe/assets/reacher.xml
mjc_mwe/assets/swimmer.xml
mjc_mwe/assets/walker2d.xml